finemo/__init__.py
finemo/__main__.py
finemo/data_io.py
finemo/evaluation.py
finemo/hitcaller.py
finemo/main.py
finemo/postprocessing.py
finemo/visualization.py
finemo/templates/__init__.py
finemo/templates/report.html
finemo-0.41.dist-info/licenses/LICENSE
finemo-0.41.dist-info/METADATA
finemo-0.41.dist-info/WHEEL
finemo-0.41.dist-info/entry_points.txt
finemo-0.41.dist-info/top_level.txt
finemo-0.41.dist-info/RECORD
