Metadata-Version: 2.4
Name: finemo
Version: 0.41
Summary: Identification of regulatory elements from neural network contribution scores for DNA.
Author-email: Austin Wang <atwang@stanford.edu>, Anshul Kundaje <akundaje@stanford.edu>
License: MIT License
Project-URL: Homepage, https://github.com/kundajelab/Fi-NeMo
Project-URL: Repository, https://github.com/kundajelab/Fi-NeMo.git
Keywords: deep learning,genomics
License-File: LICENSE
Requires-Dist: numpy
Requires-Dist: scipy
Requires-Dist: torch
Requires-Dist: numba
Requires-Dist: polars>=1.0
Requires-Dist: matplotlib
Requires-Dist: h5py
Requires-Dist: hdf5plugin
Requires-Dist: tqdm
Requires-Dist: pyBigWig
Requires-Dist: pyfaidx
Requires-Dist: jinja2
Requires-Dist: jaxtyping
Dynamic: license-file
